tmyts_utils/__init__.py
tmyts_utils/dropbox/__init__.py
tmyts_utils/dropbox/functions.py
tmyts_utils/tokenizers/__init__.py
tmyts_utils/tokenizers/tmyts_ms_tokenizer.py
tmyts_utils-0.1.7.dist-info/METADATA
tmyts_utils-0.1.7.dist-info/WHEEL
tmyts_utils-0.1.7.dist-info/RECORD
