Metadata-Version: 2.3
Name: tmyts-utils
Version: 0.1.7
Summary: Tokenizers for TMYTS' microservices
Author: baosiek
Author-email: baosiek@gmail.com
Requires-Python: >=3.12
Classifier: Programming Language :: Python :: 3
Classifier: Programming Language :: Python :: 3.12
Classifier: Programming Language :: Python :: 3.13
Requires-Dist: dropbox (>=12.0.2)
Requires-Dist: tokenizers (>=0.21.1)
